tushare_gui/__init__.py
tushare_gui/__main__.py
tushare_gui/api_desc.py
tushare_gui/api_list.py
tushare_gui-1.2.dist-info/METADATA
tushare_gui-1.2.dist-info/WHEEL
tushare_gui-1.2.dist-info/entry_points.txt
tushare_gui-1.2.dist-info/top_level.txt
tushare_gui-1.2.dist-info/RECORD
