Metadata-Version: 2.1
Name: tushare-gui
Version: 1.2
Summary: tusahre接口图形化使用工具
Home-page: UNKNOWN
Author: naska
Author-email: i@naska.me
License: UNKNOWN
Platform: UNKNOWN
Classifier: Programming Language :: Python :: 3
Classifier: License :: OSI Approved :: MIT License
Classifier: Operating System :: OS Independent
Requires-Python: >=3.6
Requires-Dist: tushare
Requires-Dist: pandas
Requires-Dist: pandastable
